{
    "add": "Ajouter",
    "button_cancel": "Annuler",
    "button_create": "Créer",
    "button_ok": "OK",
    "button_save": "Enregister",
    "delete": "Supprimer",
    "edit": "Editer",
    "label_doctor_name": "Docteur",
    "label_patient_number": "Numéro de patient",
    "label_report_date": "Date",
    "menu_files": "Fichiers",
    "menu_files_exit": "Quitter",
    "menu_files_export": "Exporter",
    "menu_files_export_report": "Exporter un rapport écrit",
    "menu_files_import_timeline": "Importer une frise",
    "menu_files_import_video": "Ouvrir une vidéo",
    "menu_files_new": "Nouveau",
    "menu_symptoms": "Symptomes",
    "menu_symptoms_add": "Ajouter un symptome",
    "symptom_tree": "Symptome",
    "tab_objective": "Objectif",
    "tab_subjective": "Subjectif",
    "toolbar_pause": "Pause",
    "toolbar_play": "Lecture",
    "window_add_symptom": "Ajouter un nouveau symptome",
    "window_edit_report": "Édition de rapport",
    "window_edit_symptom": "Edition du symptome"
}
